finance_core-0.1.8.dist-info/METADATA
finance_core-0.1.8.dist-info/WHEEL
finance_core-0.1.8.dist-info/licenses/LICENSE
finance_core/__init__.py
finance_core/_finance_core.cpython-314-i386-linux-gnu.so
finance_core/_finance_core.pyi
finance_core/main.py
finance_core/py.typed
finance_core-0.1.8.dist-info/RECORD
